README.md
setup.cfg
setup.py
pydead.egg-info/PKG-INFO
pydead.egg-info/SOURCES.txt
pydead.egg-info/dependency_links.txt
pydead.egg-info/entry_points.txt
pydead.egg-info/requires.txt
pydead.egg-info/top_level.txt
src/__init__.py
src/base.py
src/exceptions.py
src/parse.py
src/search.py
src/utils.py
src/writer.py