Metadata-Version: 1.1
Name: pydead
Version: 1.2.1
Summary: Utility for searching of unused code in python projects, such as module’s global classes, functions and names.
Home-page: https://github.com/SrgyPetrov/pydead
Author: Sergey Petrov
Author-email: srgypetrov@ya.ru
License: UNKNOWN
Platform: UNKNOWN
Classifier: Environment :: Console
Classifier: Intended Audience :: Developers
Classifier: Programming Language :: Python
Classifier: Programming Language :: Python :: 3
Classifier: Programming Language :: Python :: 3.4
Classifier: Programming Language :: Python :: 3.5
Classifier: Programming Language :: Python :: 3.6
Classifier: Topic :: Software Development
Classifier: Topic :: Utilities
